{"benchmarks.md":"BkNQeNmg","developer_interface-contracts.md":"C2bkdGGQ","getting-started_concepts.md":"BZMW0Hy8","getting-started_faq.md":"C9Nj0tWQ","getting-started_index.md":"DCFiAPrq","getting-started_infrastructure.md":"S0xxSc1h","getting-started_tutorials_competing-outcomes.md":"BzBvzL5d","getting-started_tutorials_composing-distributions.md":"CiKeB1DY","getting-started_tutorials_linear-chain.md":"BXPRwhGT","getting-started_varying-distributions.md":"D4bMxv2B","index.md":"BvC1Ls3i","lib_internals.md":"B41ni_-o","lib_public.md":"CvLhaZ-K","release-notes.md":"sOS86wTE"}
